ADD/alu6/alu6.srcs/sources_1/new/memory.v
`timescale 1ns / 1ps

module memory (
    input            clk,
    input            rst,
    input            we,
    input      [7:0] addr,
    input      [7:0] write_data,
    output     [7:0] read_data
);

reg [7:0] mem [255:0];  // 2^8

integer i;
always @(posedge clk) begin
    if (rst) begin
        for (i = 0; i < 256; i = i + 1)
            mem[i] <= 8'd0;
        // Test values
        mem[0] <= 1;
        mem[255] <= 1;
    end else if (we) begin
        mem[addr] <= write_data;
    end
end

// Asynchronous read so LOAD result is available the same cycle
assign read_data = mem[addr];

endmodule

ADD/alu6/alu6.srcs/sources_1/new/alu.v
`timescale 1ns / 1ps
// =============================================================
//  ALU - Arithmetic & Logic Unit
//  Opcode map (alu_op[2:0]):
//    000 = ADD   rd = a + b
//    001 = SUB   rd = a - b
//    010 = MOV   rd = b
//    011 = SUBI  rd = a - b  (b is sign-extended immediate)
//    100 = CMP   flags only  (no writeback - enforced by control)
//    101 = ADDI  rd = a + b  (b is sign-extended immediate)
//    110 = AND   rd = a & b
//    111 = OR    rd = a | b
//
//  Outputs:
//    result   - 8-bit ALU output (written to register only when reg_we=1)
//    zero     - 1 when result == 0
//    negative - 1 when result[7] == 1  (two's-complement sign bit)
// =============================================================
module alu (
    input      [7:0] a,
    input      [7:0] b,
    input      [2:0] alu_op,
    output reg [7:0] result,
    output           zero,
    output           negative
);

always @(*) begin
    case (alu_op)
        3'b000: result = a + b;        // ADD
        3'b001: result = a - b;        // SUB
        3'b010: result = b;            // MOV
//        3'b011: result = a - b;        // SUBI  (imm as b)
//        3'b100: result = a - b;        // CMP   (flags only, control blocks writeback)
//        3'b101: result = a + b;        // ADDI  (imm as b)
//        3'b110: result = a & b;        // AND
//        3'b111: result = a | b;        // OR
        default: result = 8'd0;
    endcase
end

assign zero     = (result == 8'd0);
assign negative =  result[7];          // MSB = sign in two's complement

endmodule

ADD/alu5/alu5.srcs/sources_1/new/register_file.v
`timescale 1ns / 1ps

module register_file (
    input            clk,
    input            rst,
    input            we,
    input      [2:0] raddr1,      // read port 1
    input      [2:0] raddr2,      // read port 2
    input      [2:0] waddr,       // write port
    input      [7:0] write_data,
    output     [7:0] read_data1,
    output     [7:0] read_data2
);

reg [7:0] regs [7:0];

// Reset initialises the calling convention state.
// Everything else starts at 0;
// Link Register (sotring the return address);
// SP starts at 0xFF (top of 256-byte memory);
integer i;
always @(posedge clk) begin
    if (rst) begin
        for (i = 0; i < 6; i = i + 1)
            regs[i] <= 8'd0;
        regs[6] <= 8'd0;    // LR = 0
        regs[7] <= 8'hFF;   // SP = 255
    end else if (we) begin
        regs[waddr] <= write_data;
    end
end

// Asynchronous read - reflects latest value including same-cycle write
assign read_data1 = regs[raddr1];
assign read_data2 = regs[raddr2];

endmodule

ADD/alu6/alu6.srcs/sources_1/new/instr_memory.v
`timescale 1ns / 1ps
// =============================================================
//  Instruction Memory
//
//  Program: iterative sum  :-  sum = 1 + 2 + ... + N
//
//    C equivalent:
//      // n pre-stored in mem[0];  mem[255] = 1 (constant)
//      int sum_n(int n) {
//          int sum = 0;
//          while (n != 0) {
//              sum += n;
//              n--;
//          }
//          mem[0] = sum;
//      }
//
//  Opcodes used - ADD, SUB, CMP, LOAD, STOR, BNE, JUMP (7 total):
//    LOAD  0x7  -  Rd  = mem[Rs]          register-indirect
//    STOR  0x8  -  mem[Rd] = Rs           register-indirect
//    ADD   0x0  -  Rd  = Rd + Rs
//    SUB   0x1  -  Rd  = Rd - Rs
//    CMP   0x5  -  flags ← Rd - Rs        no writeback
//    BNE   0xB  -  if Z==0: PC ← target
//    JUMP  0x9  -  PC ← target            unconditional (used as halt)
//
//  Register assignments (all 0 at reset, except R7 = 0xFF):
//    R0  - permanent zero / address 0  (never written, used as base addr)
//    R1  - accumulator  (sum),  init 0 at reset
//    R2  - counter      (n),    loaded from mem[0]
//    R3  - constant 1,          loaded from mem[0xFF] via R7
//    R7  - SP = 0xFF at reset, used once to load mem[255] = 1 into R3
//
//  Data memory layout (set by testbench before reset release):
//    mem[0x00] = N    e.g. N=5  →  result = 15
//    mem[0xFF] = 1    constant for decrement (SUB R2, R3)
//
//  Instruction encoding (16-bit):
//    [15:12] opcode | [11:9] rd | [8:6] rs | [5:0] imm6 (0 for reg-reg)
//  CF-format (JUMP, BNE):
//    [15:12] opcode | [11:8] 0000 | [7:0] 8-bit target
//
//  Assembly listing:
//
//  PC  Hex     Mnemonic          Notes
//  --  ------  ----------------  -----------------------------------------
//   0  7400    LOAD R2, [R0]     counter = mem[0] = N
//   1  77C0    LOAD R3, [R7]     const1  = mem[255] = 1
//   2  5400    CMP  R2, R0       pre-loop: flags ← counter - 0
//   3  B006    BNE  #6           if N≠0 → loop body
//   4  8040    STOR R1, [R0]     N=0 on entry: store sum=0 → mem[0]
//   5  9005    JUMP #5           halt
//   6  0280    ADD  R1, R2       sum  += counter         ← loop body
//   7  14C0    SUB  R2, R3       counter -= 1
//   8  5400    CMP  R2, R0       flags ← counter - 0
//   9  B006    BNE  #6           if counter≠0 → loop again
//  10  8040    STOR R1, [R0]     store final sum → mem[0]
//  11  900B    JUMP #11          halt
//
//  Encoding:
//    LOAD R2,[R0]: 0111 010 000 000000 = 0x7400
//    LOAD R3,[R7]: 0111 011 111 000000 = 0x77C0
//    CMP  R2, R0:  0101 010 000 000000 = 0x5400
//    BNE  #6:      1011 0000 0000 0110 = 0xB006
//    STOR R1,[R0]: 1000 000 001 000000 = 0x8040
//    JUMP #5:      1001 0000 0000 0101 = 0x9005
//    ADD  R1, R2:  0000 001 010 000000 = 0x0280
//    SUB  R2, R3:  0001 010 011 000000 = 0x14C0
//    JUMP #11:     1001 0000 0000 1011 = 0x900B
// =============================================================

module instr_memory (
    input      [7:0]  addr,
    output reg [15:0] instr
);

always @(*) begin
    case (addr)
        // ---- Initialisation ----
        8'd0:  instr = 16'h7400; // LOAD R2, [R0]   counter = mem[0] = N
        8'd1:  instr = 16'h77C0; // LOAD R3, [R7]   const1  = mem[255] = 1
        // ---- Pre-loop guard ----
        8'd2:  instr = 16'h5400; // CMP  R2, R0     flags ← counter - 0
        8'd3:  instr = 16'hB006; // BNE  #6         if N≠0 → loop body
        8'd4:  instr = 16'h8040; // STOR R1, [R0]   sum=0 → mem[0]
        8'd5:  instr = 16'h9005; // JUMP #5         halt
        // ---- Loop body ----
        8'd6:  instr = 16'h0280; // ADD  R1, R2     sum += counter
        8'd7:  instr = 16'h14C0; // SUB  R2, R3     counter -= 1
        // ---- Loop back-edge ----
        8'd8:  instr = 16'h5400; // CMP  R2, R0     flags ← counter - 0
        8'd9:  instr = 16'hB006; // BNE  #6         if counter≠0 → loop
        // ---- Exit ----
        8'd10: instr = 16'h8040; // STOR R1, [R0]   sum → mem[0]
        8'd11: instr = 16'h900B; // JUMP #11        halt
        default: instr = 16'h0000;
    endcase
end

endmodule

ADD/alu6/alu6.srcs/sources_1/new/control.v
`timescale 1ns / 1ps
// =============================================================
//  Control - top-level processor (single-cycle)
//
//  Opcodes active in this build:
//    ADD   0x0  -  Rd = Rd + Rs
//    SUB   0x1  -  Rd = Rd - Rs
//    CMP   0x5  -  flags ← Rd - Rs  (no writeback)
//    LOAD  0x7  -  Rd = mem[Rs]
//    STOR  0x8  -  mem[Rd] = Rs
//    BNE   0xB  -  if Z==0: PC ← target
//    JUMP  0x9  -  PC ← target
// =============================================================

module control (
    input        clk,
    input        rst,
    output [7:0] alu_result_out,
    output [7:0] pc_out
);

// ---------------------------------------------------------------
// Opcode parameters (must match instr_memory.v)
// ---------------------------------------------------------------
localparam ADD  = 4'h0,
           SUB  = 4'h1,
           CMP  = 4'h5,
           LOAD = 4'h7,
           STOR = 4'h8,
           JUMP = 4'h9,
           BNE  = 4'hB;

// ---------------------------------------------------------------
// Program counter
// ---------------------------------------------------------------
reg  [7:0] pc;
wire [7:0] next_pc;

// ---------------------------------------------------------------
// Instruction fetch
// ---------------------------------------------------------------
wire [15:0] instr;
instr_memory imem (
    .addr  (pc),
    .instr (instr)
);

// ---------------------------------------------------------------
// Instruction decode
// ---------------------------------------------------------------
wire [3:0] opcode = instr[15:12];
wire [2:0] rd     = instr[11:9];
wire [2:0] rs     = instr[8:6];

// Branch / jump target occupies lower 8 bits
wire [7:0] cf_target = instr[7:0];

// ---------------------------------------------------------------
// Control signals (combinational decode)
// ---------------------------------------------------------------
reg        reg_we;       // 1 = write ALU result to reg[rd]
reg        mem_we;       // 1 = write to data memory
reg        mem_to_reg;   // 1 = writeback from data memory (LOAD)
reg        use_mem_addr; // 1 = memory address is a register value
reg [2:0]  alu_op;       // ALU operation select

always @(*) begin
    reg_we       = 1'b0;
    mem_we       = 1'b0;
    mem_to_reg   = 1'b0;
    use_mem_addr = 1'b0;
    alu_op       = 3'b000;

    case (opcode)
        ADD:  begin reg_we = 1'b1; alu_op = 3'b000; end
        SUB:  begin reg_we = 1'b1; alu_op = 3'b001; end
        CMP:  begin               alu_op = 3'b001; end  // flags only, no reg_we
        LOAD: begin reg_we = 1'b1; mem_to_reg = 1'b1; use_mem_addr = 1'b1; end
        STOR: begin mem_we = 1'b1;                     use_mem_addr = 1'b1; end
        JUMP: begin end
        BNE:  begin end
        default: begin end
    endcase
end

// ---------------------------------------------------------------
// Register file
// ---------------------------------------------------------------
wire [7:0] reg_data_rd;  // value of reg[rd]  - ALU input A, mem addr for STOR
wire [7:0] reg_data_rs;  // value of reg[rs]  - ALU input B, store data, LOAD addr

wire [7:0] mem_rdata;    // forward declaration (defined at memory block below)

wire [7:0] wb_data = mem_to_reg ? mem_rdata : alu_result;

register_file rf (
    .clk        (clk),
    .rst        (rst),
    .we         (reg_we),
    .raddr1     (rd),
    .raddr2     (rs),
    .waddr      (rd),
    .write_data (wb_data),
    .read_data1 (reg_data_rd),
    .read_data2 (reg_data_rs)
);

// ---------------------------------------------------------------
// ALU  (operand B is always a register for this program)
// ---------------------------------------------------------------
wire [7:0] alu_result;
wire       alu_zero;
wire       alu_negative;

alu alu_unit (
    .a        (reg_data_rd),
    .b        (reg_data_rs),
    .alu_op   (alu_op),
    .result   (alu_result),
    .zero     (alu_zero),
    .negative (alu_negative)
);

// ---------------------------------------------------------------
// Flag register
// Updated only by CMP; held stable during branch instructions.
// ---------------------------------------------------------------
reg flag_zero;

always @(posedge clk) begin
    if (rst)
        flag_zero <= 1'b0;
    else if (opcode == CMP)
        flag_zero <= alu_zero;
end

// ---------------------------------------------------------------
// Data memory
//   LOAD rd,[rs]  →  address = reg[rs] = reg_data_rs
//   STOR rs,[rd]  →  address = reg[rd] = reg_data_rd
// ---------------------------------------------------------------
wire is_load = (opcode == LOAD);
wire [7:0] mem_addr = use_mem_addr ? (is_load ? reg_data_rs : reg_data_rd) : 8'd0;

memory dmem (
    .clk        (clk),
    .rst        (rst),
    .we         (mem_we),
    .addr       (mem_addr),
    .write_data (reg_data_rs),
    .read_data  (mem_rdata)
);

// ---------------------------------------------------------------
// PC / branch logic  (reads registered flag_zero)
// ---------------------------------------------------------------
assign next_pc =
    (opcode == JUMP)               ? cf_target :
    (opcode == BNE && !flag_zero)  ? cf_target :
    pc + 8'd1;

always @(posedge clk) begin
    if (rst) pc <= 8'd0;
    else     pc <= next_pc;
end

// ---------------------------------------------------------------
// Debug outputs
// ---------------------------------------------------------------
assign alu_result_out = alu_result;
assign pc_out         = pc;

endmodule

ADD/alu6/alu6.srcs/sim_1/new/tb_control.v
`timescale 1ns / 1ps
// =============================================================
//  Testbench - iterative sum_n processor
//
//  Tests sum = 1 + 2 + ... + N for N = 0, 1, 3, 5, 10
//  Expected results  (N*(N+1)/2):
//    N=0  → 0
//    N=1  → 1
//    N=3  → 6
//    N=5  → 15
//    N=10 → 55
//
//  Strategy per test case:
//    1. Assert rst, write mem[0]=N and mem[255]=1 via force,
//       then de-assert rst so the processor begins from PC=0.
//    2. Run for enough clock cycles for the program to complete
//       (worst case: 2 init + 1 guard-CMP + 1 guard-BNE +
//        N*(ADD+SUB+CMP+BNE) + STOR + JUMP  =  N*4 + 6 cycles).
//    3. Read mem[0] from the data memory and compare to expected.
// =============================================================

module tb_control;

// ---------------------------------------------------------------
// DUT signals
// ---------------------------------------------------------------
reg        clk;
reg        rst;
wire [7:0] alu_result_out;
wire [7:0] pc_out;

// ---------------------------------------------------------------
// DUT instantiation
// ---------------------------------------------------------------
control dut (
    .clk           (clk),
    .rst           (rst),
    .alu_result_out(alu_result_out),
    .pc_out        (pc_out)
);

// ---------------------------------------------------------------
// Clock  - 10 ns period (100 MHz)
// ---------------------------------------------------------------
initial clk = 0;
always  #5 clk = ~clk;

// ---------------------------------------------------------------
// Helpers
// ---------------------------------------------------------------
integer pass_count;
integer fail_count;

// Max cycles to wait for the processor to halt at the JUMP #11
// instruction.  Formula: N*4 + 10 (generous headroom).
function [31:0] max_cycles;
    input [7:0] n;
    begin
        max_cycles = (n * 4) + 20;
    end
endfunction

// Wait until the PC stops changing (processor has halted in the
// JUMP self-loop) or the cycle budget is exhausted.
task wait_for_halt;
    input [31:0] budget;
    integer i;
    reg [7:0] prev_pc;
    begin
        prev_pc = 8'hFF;   // impossible initial value
        for (i = 0; i < budget; i = i + 1) begin
            @(posedge clk);
            #1;            // tiny settle after posedge
            if (pc_out == prev_pc) begin
                i = budget; // break: PC has stopped moving
            end
            prev_pc = pc_out;
        end
    end
endtask

// Run one test case.
//   n        - input value stored in mem[0]
//   expected - expected sum
//   label    - string printed in pass/fail line
task run_test;
    input [7:0]  n;
    input [7:0]  expected;
    input [63:0] label;      // up to 8 ASCII chars packed into 64 bits
    reg   [7:0]  result;
    begin
        // ---- 1. Hold reset ----
        rst = 1;
        @(posedge clk); #1;
        @(posedge clk); #1;

        // ---- 2. Initialise data memory while reset is held ----
        //  mem[0x00] = N   (the input)
        //  mem[0xFF] = 1   (constant used for SUB R2, R3)
        force dut.dmem.mem[8'h00] = n;
        force dut.dmem.mem[8'hFF] = 8'd1;

        // ---- 3. Release reset ----
        @(negedge clk);
        rst = 0;
        release dut.dmem.mem[8'h00];
        release dut.dmem.mem[8'hFF];

        // ---- 4. Run until halt ----
        wait_for_halt(max_cycles(n));

        // ---- 5. Read result ----
        result = dut.dmem.mem[8'h00];

        // ---- 6. Report ----
        if (result === expected) begin
            $display("PASS  N=%-3d  expected=%3d  got=%3d  (PC=%0d)",
                     n, expected, result, pc_out);
            pass_count = pass_count + 1;
        end else begin
            $display("FAIL  N=%-3d  expected=%3d  got=%3d  (PC=%0d)",
                     n, expected, result, pc_out);
            fail_count = fail_count + 1;
        end
    end
endtask

// ---------------------------------------------------------------
// Test sequence
// ---------------------------------------------------------------
initial begin
    pass_count = 0;
    fail_count = 0;

    $display("================================================");
    $display("  Testbench: iterative sum_n");
    $display("  sum(N) = 1 + 2 + ... + N");
    $display("================================================");

    // Edge case: N = 0  (should return 0 immediately via guard branch)
//    run_test(8'd0,   8'd0,   "N=0     ");

    // Minimal: N = 1
    run_test(8'd1,   8'd1,   "N=1     ");

    // Small: N = 3  → 6
//    run_test(8'd3,   8'd6,   "N=3     ");

    // Typical: N = 5  → 15
//    run_test(8'd5,   8'd15,  "N=5     ");

    // Larger: N = 10 → 55
//    run_test(8'd10,  8'd55,  "N=10    ");

    // Max safe (8-bit result fits: N=20 → 210, N=21 → 231, N=22 → 253)
//    run_test(8'd20,  8'd210, "N=20    ");

    $display("================================================");
    $display("  Results: %0d passed,  %0d failed", pass_count, fail_count);
    $display("================================================");

    $finish;
end

// ---------------------------------------------------------------
// Waveform dump (optional - remove if not needed)
// ---------------------------------------------------------------
initial begin
    $dumpfile("tb_control.vcd");
    $dumpvars(0, tb_control);
end

// ---------------------------------------------------------------
// Timeout watchdog - kills simulation if something hangs
// ---------------------------------------------------------------
initial begin
    #100000;
    $display("TIMEOUT - simulation exceeded 100 us");
    $finish;
end

endmodule

ADD/alu6/alu6.sim/sim_1/behav/xsim/tb_control.vcd
$date
   Fri Mar 27 14:33:40 2026
$end
$version
  2021.2
$end
$timescale
  1ps
$end
$scope module tb_control $end
$var reg 1 ! clk $end
$var reg 1 " rst $end
$var wire 8 # alu_result_out [7:0] $end
$var wire 8 $ pc_out [7:0] $end
$var integer 32 % pass_count [31:0] $end
$var integer 32 & fail_count [31:0] $end
$scope module dut $end
$var wire 1 ' clk $end
$var wire 1 ( rst $end
$var wire 8 # alu_result_out [7:0] $end
$var wire 8 $ pc_out [7:0] $end
$var reg 8 ) pc [7:0] $end
$var wire 8 * next_pc [7:0] $end
$var wire 16 + instr [15:0] $end
$var wire 4 , opcode [3:0] $end
$var wire 3 - rd [2:0] $end
$var wire 3 . rs [2:0] $end
$var wire 8 / cf_target [7:0] $end
$var reg 1 0 reg_we $end
$var reg 1 1 mem_we $end
$var reg 1 2 mem_to_reg $end
$var reg 1 3 use_mem_addr $end
$var reg 3 4 alu_op [2:0] $end
$var wire 8 5 reg_data_rd [7:0] $end
$var wire 8 6 reg_data_rs [7:0] $end
$var wire 8 7 mem_rdata [7:0] $end
$var wire 8 8 wb_data [7:0] $end
$var wire 8 9 alu_result [7:0] $end
$var wire 1 : alu_zero $end
$var wire 1 ; alu_negative $end
$var reg 1 < flag_zero $end
$var wire 1 = is_load $end
$var wire 8 > mem_addr [7:0] $end
$scope module imem $end
$var wire 8 ? addr [7:0] $end
$var reg 16 @ instr [15:0] $end
$upscope $end
$scope module rf $end
$var wire 1 ' clk $end
$var wire 1 ( rst $end
$var wire 1 A we $end
$var wire 3 - raddr1 [2:0] $end
$var wire 3 . raddr2 [2:0] $end
$var wire 3 - waddr [2:0] $end
$var wire 8 8 write_data [7:0] $end
$var wire 8 5 read_data1 [7:0] $end
$var wire 8 6 read_data2 [7:0] $end
$var integer 32 B i [31:0] $end
$upscope $end
$scope module alu_unit $end
$var wire 8 5 a [7:0] $end
$var wire 8 6 b [7:0] $end
$var wire 3 C alu_op [2:0] $end
$var reg 8 D result [7:0] $end
$var wire 1 : zero $end
$var wire 1 ; negative $end
$upscope $end
$scope module dmem $end
$var wire 1 ' clk $end
$var wire 1 ( rst $end
$var wire 1 E we $end
$var wire 8 > addr [7:0] $end
$var wire 8 6 write_data [7:0] $end
$var wire 8 7 read_data [7:0] $end
$var integer 32 F i [31:0] $end
$upscope $end
$upscope $end
$scope function max_cycles $end
$var reg 32 G max_cycles [31:0] $end
$var reg 8 H n [7:0] $end
$upscope $end
$scope task wait_for_halt $end
$var reg 32 I budget [31:0] $end
$var integer 32 J i [31:0] $end
$var reg 8 K prev_pc [7:0] $end
$upscope $end
$scope task run_test $end
$var reg 8 L n [7:0] $end
$var reg 8 M expected [7:0] $end
$var reg 64 N label [63:0] $end
$var reg 8 O result [7:0] $end
$upscope $end
$upscope $end
$enddefinitions $end
#0
$dumpvars
0!
1"
bx #
bx $
b0 %
b0 &
0'
1(
bx )
bx *
bx +
bx ,
bx -
bx .
bx /
x0
x1
x2
x3
bx 4
bx 5
bx 6
bx 7
bx 8
bx 9
x:
x;
x<
x=
bx >
bx ?
bx @
xA
bx B
bx C
bx D
xE
bx F
bx G
bx H
bx I
bx J
bx K
b1 L
b1 M
b100111000111101001100010010000000100000001000000010000000100000 N
bx O
$end
#5000
1!
b0 #
b0 $
1'
b0 )
b1 *
b111010000000000 +
b111 ,
b10 -
b0 .
b0 /
10
01
12
13
b0 4
b0 5
b0 6
b0 7
b0 8
b0 9
1:
0;
0<
1=
b0 >
b0 ?
b111010000000000 @
1A
b0 C
b0 D
0E
#10000
0!
0'
#15000
1!
1'
#20000
0!
0"
0'
0(
b11000 G
b1 H
b11000 I
b0 J
b11111111 K
#25000
1!
b11111111 #
b1 $
1'
b1 )
b10 *
b111011111000000 +
b11 -
b111 .
b11000000 /
b0 5
b11111111 6
b0 7
b11111111 9
0:
1;
b11111111 >
b1 ?
b111011111000000 @
b11111111 D
#26000
b1 J
b1 K
#30000
0!
0'
#35000
1!
b0 #
b10 $
1'
b10 )
b11 *
b101010000000000 +
b101 ,
b10 -
b0 .
b0 /
00
02
03
b1 4
b0 5
b0 6
b0 7
b0 8
b0 9
1:
0;
0=
b0 >
b10 ?
b101010000000000 @
0A
b1 C
b0 D
#36000
b10 J
b10 K
#40000
0!
0'
#45000
1!
b11 $
1'
b11 )
b100 *
b1011000000000110 +
b1011 ,
b0 -
b110 /
b0 4
b0 5
1<
0=
b11 ?
b1011000000000110 @
b0 C
b0 D
#46000
b11 J
b11 K
#50000
0!
0'
#55000
1!
b100 $
1'
b100 )
b101 *
b1000000001000000 +
b1000 ,
b1 .
b1000000 /
11
13
b0 4
b0 6
0=
b0 >
b100 ?
b1000000001000000 @
1E
#56000
b100 J
b100 K
#60000
0!
0'
#65000
1!
b101 $
1'
b101 )
b101 *
b1001000000000101 +
b1001 ,
b0 .
b101 /
01
03
b0 4
b0 6
0=
b0 >
b101 ?
b1001000000000101 @
0E
#66000
b101 J
b101 K
#70000
0!
0'
#75000
1!
1'
#76000
b1 &
b11001 J
b0 O
